compotime/__init__.py
compotime/errors.py
compotime/models.py
compotime/preprocess.py
compotime-0.3.0.dist-info/LICENSE
compotime-0.3.0.dist-info/METADATA
compotime-0.3.0.dist-info/WHEEL
compotime-0.3.0.dist-info/RECORD
